README.md
setup.cfg
setup.py
fuse/__init__.py
fuse/defect_augment.py
fuse/duplicate.py
fuse/elastic_augment.py
fuse/lazy_string_representation.py
fuse/log.py
fuse/map_numpy_array.py
fuse/mask_out_labels.py
fuse/misalign.py
fuse/new_key_from_numpy_array.py
fuse/numpy_require.py
fuse/simple_augment.py
fuse/snapshot.py
fuse/snapshot_as_dict.py
fuse/snapshot_with_attributes_callback.py
fuse/util.py
fuse/version_info.py
fuse/z5py_io.py
fuse.egg-info/PKG-INFO
fuse.egg-info/SOURCES.txt
fuse.egg-info/dependency_links.txt
fuse.egg-info/requires.txt
fuse.egg-info/top_level.txt
fuse/ext/__init__.py