Metadata-Version: 2.1
Name: fuse
Version: 0.1.3
Summary: Fuse to get gunpowder started
Home-page: https://github.com/hanslovsky/fuse
Author: Philipp Hanslovsky
Author-email: hanslovskyp@janelia.hhmi.org
License: bsd-2
Platform: UNKNOWN
Requires-Python: >=3.6
